te_quiz/__init__.py
te_quiz/constants.py
te_quiz/evaluator.py
te_quiz/exceptions.py
te_quiz-1.1.0.dist-info/LICENSE
te_quiz-1.1.0.dist-info/METADATA
te_quiz-1.1.0.dist-info/WHEEL
te_quiz-1.1.0.dist-info/RECORD
