Metadata-Version: 2.3
Name: te_quiz
Version: 1.1.0
Summary: A package for evaluating quiz results and communication styles
License: MIT
Keywords: quiz,evaluation,communication,assessment
Author: Garima Jain
Author-email: igarimajain26@gmail.com
Requires-Python: >=3.10,<4.0
Classifier: Development Status :: 5 - Production/Stable
Classifier: Intended Audience :: Developers
Classifier: License :: OSI Approved :: MIT License
Classifier: Operating System :: OS Independent
Classifier: Programming Language :: Python :: 3
Classifier: Programming Language :: Python :: 3.10
Classifier: Programming Language :: Python :: 3.11
Classifier: Programming Language :: Python :: 3.12
Classifier: Programming Language :: Python :: 3.13
